sayhi/__init__.py
sayhi/say_hi.py
sayhi/sayhello.py
sayhi-0.0.2.dist-info/LICENSE
sayhi-0.0.2.dist-info/METADATA
sayhi-0.0.2.dist-info/WHEEL
sayhi-0.0.2.dist-info/top_level.txt
sayhi-0.0.2.dist-info/RECORD
