Metadata-Version: 2.1
Name: sayhi
Version: 0.0.2
Summary: 演示的package
Home-page: https://github.com/jack/say_hi
Author: Jack
Author-email: jack@live.com
License: UNKNOWN
Platform: UNKNOWN
Classifier: Programming Language :: Python :: 3
Classifier: License :: OSI Approved :: MIT License
Classifier: Operating System :: OS Independent
Requires-Python: >=3
Requires-Dist: requests
